dawgmon/__init__.py
dawgmon/__main__.py
dawgmon/cache.py
dawgmon/dawgmon.py
dawgmon/local.py
dawgmon/utils.py
dawgmon/version.py
dawgmon/commands/__init__.py
dawgmon/commands/block.py
dawgmon/commands/debian.py
dawgmon/commands/env.py
dawgmon/commands/files.py
dawgmon/commands/ipc.py
dawgmon/commands/mount.py
dawgmon/commands/network.py
dawgmon/commands/processes.py
dawgmon/commands/systemd.py
dawgmon/commands/sysv.py
dawgmon/commands/ubuntu.py
dawgmon/commands/uptime.py
dawgmon/commands/users.py
dawgmon/commands/version.py
dawgmon-1.1.dist-info/LICENSE
dawgmon-1.1.dist-info/METADATA
dawgmon-1.1.dist-info/WHEEL
dawgmon-1.1.dist-info/entry_points.txt
dawgmon-1.1.dist-info/top_level.txt
dawgmon-1.1.dist-info/RECORD
